Metadata-Version: 1.0
Name: distribution-probability
Version: 1.0
Summary: Gaussian and Binomial Distribution
Home-page: UNKNOWN
Author: Iromi Paranavithana
Author-email: iromirandika@gmail.com
License: UNKNOWN
Platform: UNKNOWN
